<dataset type="EDDGridFromNcFiles" datasetID=" " active="true">
    <reloadEveryNMinutes>10080</reloadEveryNMinutes>

    <fileDir>/usr/share/tomcat6/content/erddap/soe</fileDir>
    <fileNameRegex> </fileNameRegex>
    <recursive>true</recursive>

    <metadataFrom>last</metadataFrom>

    <fileTableInMemory>false</fileTableInMemory>
    
     <addAttributes>
        <att name="cdm_data_type"> </att>
        <att name="Conventions">CF-1.6, COARDS, ACDD-1.3</att>
        <att name="infoUrl"> </att>
        <att name="institution">NEFSC</att>
        <att name="keywords"> </att>
        <att name="license">[standard]</att>
        <att name="standard_name_vocabulary">CF Standard Name Table v29</att>
        <att name="summary"> </att>
        <att name="title"> </att>
    </addAttributes>
    <axisVariable>
        <sourceName>latitude</sourceName>
        <destinationName>latitude</destinationName>
        <addAttributes>
            <att name="ioos_category">Location</att>
            <att name="long_name">Latitude</att>
            <att name="standard_name">latitude</att>
        </addAttributes>
    </axisVariable>
    <axisVariable>
        <sourceName>longitude</sourceName>
        <destinationName>longitude</destinationName>
        <addAttributes>
            <att name="ioos_category">Location</att>
            <att name="long_name">Longitude</att>
            <att name="standard_name">longitude</att>
        </addAttributes>
    </axisVariable>
    <dataVariable>
        <sourceName> </sourceName>
        <destinationName> </destinationName>
        <dataType>float</dataType>
        <addAttributes>
            <att name="ioos_category">Unknown</att>
        </addAttributes>
    </dataVariable>
</dataset>